rlxbt-0.1.0.dist-info/METADATA
rlxbt-0.1.0.dist-info/WHEEL
rlxbt/__init__.py
rlxbt/core.py
rlxbt/institutional/__init__.py
rlxbt/institutional/optimization.py
rlxbt/institutional/portfolio.py
rlxbt/institutional/risk.py
rlxbt/ml/__init__.py
rlxbt/ml/strategy.py
rlxbt/ml/walk_forward.py
rlxbt/rl/graph_wrapper.py
rlxbt/rl/models.py
rlxbt/rl_env.py
rlxbt/rlx.cp311-win_amd64.pyd
rlxbt/rlxviz/__init__.py
rlxbt/rlxviz/dist/assets/index-AT1nIzYN.css
rlxbt/rlxviz/dist/assets/index-C_bUBu_q.js
rlxbt/rlxviz/dist/index.html
rlxbt/rlxviz/dist/rlx-icon.svg
rlxbt/rlxviz/dist/rlx-logo.svg
rlxbt/rlxviz/package-lock.json
rlxbt/stability.py
rlxbt/utils/__init__.py
rlxbt/utils/data_loader.py
rlxbt-0.1.0.dist-info/RECORD
