Metadata-Version: 2.4
Name: rlxbt
Version: 0.1.0
Classifier: Programming Language :: Rust
Classifier: Programming Language :: Python :: Implementation :: CPython
Classifier: Programming Language :: Python :: Implementation :: PyPy
Classifier: Topic :: Office/Business :: Financial :: Investment
Classifier: Operating System :: OS Independent
Requires-Dist: numpy
Requires-Dist: pandas
Requires-Dist: scikit-learn
Requires-Dist: stable-baselines3[extra]
Requires-Dist: gymnasium
Requires-Dist: matplotlib
Requires-Dist: seaborn
Summary: Fast trading backtester written in Rust
Author-email: Serg <sott095@gmail.com>
License: MIT
Requires-Python: >=3.8
Project-URL: Homepage, https://rlxbt.com
Project-URL: Repository, https://github.com/your-repo/rlx
